abidrive/__init__.py
abidrive/code_generator.py
abidrive/configuration.py
abidrive/dfu.py
abidrive/enums.py
abidrive/shell.py
abidrive/tests.py
abidrive/utils.py
abidrive/version.py
abidrive/version.txt
abidrive/dfuse/DfuDevice.py
abidrive/dfuse/DfuFile.py
abidrive/dfuse/DfuState.py
abidrive/dfuse/DfuStatus.py
abidrive/dfuse/__init__.py
abidrive-0.4.11.data/scripts/abidrive_demo.py
abidrive-0.4.11.data/scripts/abidrivetool
abidrive-0.4.11.data/scripts/abidrivetool.bat
abidrive-0.4.11.dist-info/DESCRIPTION.rst
abidrive-0.4.11.dist-info/METADATA
abidrive-0.4.11.dist-info/RECORD
abidrive-0.4.11.dist-info/WHEEL
abidrive-0.4.11.dist-info/metadata.json
abidrive-0.4.11.dist-info/top_level.txt
fibre/__init__.py
fibre/discovery.py
fibre/protocol.py
fibre/remote_object.py
fibre/serial_transport.py
fibre/shell.py
fibre/tcp_transport.py
fibre/udp_transport.py
fibre/usbbulk_transport.py
fibre/utils.py
